flask_os/__init__.py
flask_os/app.py
flask_os/cli.py
flask_os/setting.py
flask_os/conf/project.zip
flask_os/conf/requirements.txt
flask_os-0.2.24022223.dist-info/METADATA
flask_os-0.2.24022223.dist-info/WHEEL
flask_os-0.2.24022223.dist-info/entry_points.txt
flask_os-0.2.24022223.dist-info/top_level.txt
flask_os-0.2.24022223.dist-info/RECORD
