Metadata-Version: 2.1
Name: flask-os
Version: 0.2.24022223
Summary: flask项目基础一键生成
Home-page: https://github.com/BingerYang/flask-os
Author: binger
Author-email: <xuehen_521@126.com>
Maintainer: binger
Maintainer-email: <xuehen_521@126.com>
Platform: all
Requires-Python: >=3.4
